langextract_llamacpp/__init__.py
langextract_llamacpp/provider.py
langextract_llamacpp-0.1.2.dist-info/WHEEL
langextract_llamacpp-0.1.2.dist-info/entry_points.txt
langextract_llamacpp-0.1.2.dist-info/METADATA
langextract_llamacpp-0.1.2.dist-info/RECORD
