Metadata-Version: 2.4
Name: langextract-llamacpp
Version: 0.1.2
Summary: LangExtract provider plugin for llama-cpp-python
Author: fgarnadi
Author-email: fgarnadi <fajar.garnadi@gmail.com>
License-Expression: MIT
Requires-Dist: huggingface-hub<1.0.0
Requires-Dist: langextract>=1.1.0
Requires-Dist: llama-cpp-python>=0.3.16
Requires-Python: >=3.10
